StructureFingerprint/__init__.py
StructureFingerprint/linear.py
StructureFingerprint/morgan.py
StructureFingerprint-2.1.dist-info/METADATA
StructureFingerprint-2.1.dist-info/WHEEL
StructureFingerprint-2.1.dist-info/top_level.txt
StructureFingerprint-2.1.dist-info/RECORD
