Metadata-Version: 2.1
Name: StructureFingerprint
Version: 2.1
Summary: UNKNOWN
Home-page: https://github.com/dcloudf/MorganFingerprint
License: LGPLv3
Platform: UNKNOWN
Classifier: Environment :: Plugins
Classifier: Intended Audience :: Science/Research
Classifier: Intended Audience :: Developers
Classifier: Topic :: Scientific/Engineering :: Chemistry
Classifier: Topic :: Software Development :: Libraries :: Python Modules
Classifier: License :: OSI Approved :: GNU Lesser General Public License v3 or later (LGPLv3+)
Classifier: Operating System :: OS Independent
Classifier: Programming Language :: Python
Classifier: Programming Language :: Python :: 3
Classifier: Programming Language :: Python :: 3.6
Classifier: Programming Language :: Python :: 3.7
Classifier: Programming Language :: Python :: 3.8
Classifier: Programming Language :: Python :: 3.9
Requires-Python: >=3.6.0
Requires-Dist: CGRtools (>=4.0.41)
Requires-Dist: numpy (>=1.18)
